pydantic_serializer/VERSION
pydantic_serializer/__init__.py
pydantic_serializer/encoders.py
pydantic_serializer/main.py
tests/__init__.py
tests/create_test_db.py
tests/test_json_encoder.py
tests/test_main.py
flask_pydantic_serializer-0.0.4.dist-info/LICENSE
flask_pydantic_serializer-0.0.4.dist-info/METADATA
flask_pydantic_serializer-0.0.4.dist-info/WHEEL
flask_pydantic_serializer-0.0.4.dist-info/top_level.txt
flask_pydantic_serializer-0.0.4.dist-info/RECORD
