Metadata-Version: 2.1
Name: flask-pydantic-serializer
Version: 0.0.4
Summary: This package provides a utility to serialize db object using pydantic models.
Home-page: https://github.com/vivekkeshore/flask-pydantic-serializer
Author: Vivek Keshore
Author-email: vivek.keshore@gmail.com
License: MIT
Keywords: sqlalchemy,alchemy,mysql,postgres,flask,mssql,sql,sqlite,serialize,pydantic,orm,serialization,performance,database,relational
Platform: any
Classifier: Development Status :: 5 - Production/Stable
Classifier: Environment :: Console
Classifier: Intended Audience :: Developers
Classifier: Programming Language :: Python
Classifier: Programming Language :: Python :: 3
Classifier: Programming Language :: Python :: 3 :: Only
Classifier: Programming Language :: Python :: 3.6
Classifier: Programming Language :: Python :: 3.7
Classifier: Programming Language :: Python :: 3.8
Classifier: Programming Language :: Python :: 3.9
Classifier: Programming Language :: Python :: 3.10
Classifier: Programming Language :: Python :: Implementation :: CPython
Classifier: Programming Language :: Python :: Implementation :: PyPy
Classifier: Topic :: Software Development :: Libraries :: Python Modules
Classifier: Topic :: Utilities
Classifier: License :: OSI Approved :: MIT License
Requires-Python: >=3.6
Requires-Dist: pydantic
Provides-Extra: dev
Requires-Dist: codecoverage ; extra == 'dev'
Requires-Dist: pytest ; extra == 'dev'
